ranpy/README.md
ranpy/__init__.py
ranpy/ranpy.py
ranpy-0.0.10.dist-info/METADATA
ranpy-0.0.10.dist-info/WHEEL
ranpy-0.0.10.dist-info/licenses/LICENSE
ranpy-0.0.10.dist-info/RECORD
