Metadata-Version: 2.1
Name: ranpy
Version: 0.0.10
Summary: Making random things easier in Python.
Project-URL: Homepage, https://github.com/ranpy-3000/ranpy
Project-URL: Bug Tracker, https://github.com/ranpy-3000/ranpy/issues
Author-email: Brendan Patch <brendanpatch@gmail.com>
License: Copyright (c) 2018 The Python Packaging Authority
Classifier: License :: OSI Approved :: MIT License
Classifier: Operating System :: OS Independent
Classifier: Programming Language :: Python :: 3
Requires-Python: >=3.10
